[
  {
    "id": 0,
    "title": "ステッカー",
    "goods": [
      { 
        "id": 0,
        "title": "ステッカー（タワーレコード）",
        "image": "",
        "link": ""
      },
      { 
        "id": 1,
        "title": "ステッカー（HMV）",
        "image": "",
        "link": ""
      },
      { 
        "id": 2,
        "title": "ステッカー（TSUTAYA）",
        "image": "",
        "link": ""
      },
      { 
        "id": 3,
        "title": "ステッカー（DISH//応援店用）",
        "image": "",
        "link": ""
      }
    ]
  },
  {
    "id": 1,
    "title": "クリアファイル",
    "goods": [
      { 
        "id": 0,
        "title": "クリアファイル（楽天用）",
        "image": "",
        "link": ""
      },
      { 
        "id": 1,
        "title": "クリアファイル（アニメイト用）",
        "image": "",
        "link": ""
      }
    ]
  },
  {
    "id": 2,
    "title": "メガジャケ（Amazon用）",
    "goods": [
      { 
        "id": 0,
        "title": "初回盤メガジャケ",
        "image": "",
        "link": ""
      },
      { 
        "id": 1,
        "title": "通常盤メガジャケ",
        "image": "",
        "link": ""
      },
      { 
        "id": 2,
        "title": "アニメ盤メガジャケ",
        "image": "",
        "link": ""
      }
    ]
  }
]